{
  "openapi": "3.0.0",
  "info": {
    "version": "1.0.0",
    "title": "Hotel Prices Search API",
    "description": "Connectes to the Hotel Prices search library."
  },
  "servers": [
    {
      "url": "http://localhost:7777/api/v1/",
      "description": "Local server"
    }
  ],
  "paths": {
    "/day": {
      "get": {
        "summary": "Gets today's average hotel price.",
        "responses": {
          "200": {
            "description": "A price",
            "content": {
              "application/json": {
                "schema": {
                  "$ref": "#/components/schemas/Price"
                }
              }
            }
          }
        }
      }
    },
    "/week": {
      "get": {
        "summary": "Gets the next week of average hotel prices.",
        "responses": {
          "200": {
            "description": "A JSON array of prices.",
            "content": {
              "application/json": {
                "schema": {
                  "type": "array",
                  "items": {
                    "$ref": "#/components/schemas/Price"
                  }
                }
              }
            }
          }
        }
      }
    }
  },
  "components": {
    "schemas": {
      "Price": {
        "properties": {
          "_id": {
            "type": "string"
          },
          "price": {
            "type": "float"
          },
          "date": {
            "type": "string"
          },
          "updated": {
            "type": "string"
          }
        }
      }
    }
  }
}
